environ/__init__.py
environ/_environ_config.py
environ/exceptions.py
environ/py.typed
environ/secrets/__init__.py
environ/secrets/_utils.py
environ/secrets/awssm.py
environ_config-23.1.0.dist-info/METADATA
environ_config-23.1.0.dist-info/WHEEL
environ_config-23.1.0.dist-info/licenses/LICENSE
environ_config-23.1.0.dist-info/licenses/NOTICE
environ_config-23.1.0.dist-info/RECORD
