Metadata-Version: 2.1
Name: environ-config
Version: 23.1.0
Summary: Boilerplate-free configuration with env variables.
Project-URL: Documentation, https://environ-config.readthedocs.io/
Project-URL: Changelog, https://environ-config.rtfd.io/en/stable/changelog.html
Project-URL: Bug Tracker, https://github.com/hynek/environ-config/issues
Project-URL: Source Code, https://github.com/hynek/environ-config
Project-URL: Funding, https://github.com/sponsors/hynek
Project-URL: Tidelift, https://tidelift.com/subscription/pkg/pypi-environ-config?utm_source=pypi-environ-config&utm_medium=pypi
Author-email: Hynek Schlawack <hs@ox.cx>
License-Expression: Apache-2.0
License-File: LICENSE
License-File: NOTICE
Keywords: app,cfg,config,env
Classifier: Development Status :: 5 - Production/Stable
Classifier: Intended Audience :: Developers
Classifier: License :: OSI Approved :: Apache Software License
Classifier: Natural Language :: English
Classifier: Operating System :: OS Independent
Classifier: Programming Language :: Python
Classifier: Programming Language :: Python :: 3
Classifier: Programming Language :: Python :: 3.7
Classifier: Programming Language :: Python :: 3.8
Classifier: Programming Language :: Python :: 3.9
Classifier: Programming Language :: Python :: 3.10
Classifier: Programming Language :: Python :: 3.11
Classifier: Programming Language :: Python :: Implementation :: CPython
Classifier: Programming Language :: Python :: Implementation :: PyPy
Classifier: Topic :: Software Development :: Libraries :: Python Modules
Requires-Python: >=3.7
Requires-Dist: attrs>=17.4.0
Requires-Dist: importlib-metadata; python_version < '3.8'
Provides-Extra: aws
Requires-Dist: boto3; extra == 'aws'
Provides-Extra: dev
Requires-Dist: environ-config[docs,tests]; extra == 'dev'
Provides-Extra: docs
Requires-Dist: environ-config[aws]; extra == 'docs'
Requires-Dist: furo; extra == 'docs'
Requires-Dist: myst-parser; extra == 'docs'
Requires-Dist: sphinx; extra == 'docs'
Requires-Dist: sphinx-notfound-page; extra == 'docs'
Provides-Extra: tests
Requires-Dist: coverage[toml]; extra == 'tests'
Requires-Dist: moto; extra == 'tests'
Requires-Dist: pytest; extra == 'tests'
